manim_code_blocks.py
manim_code_blocks-1.0.13.dist-info/LICENSE
manim_code_blocks-1.0.13.dist-info/METADATA
manim_code_blocks-1.0.13.dist-info/WHEEL
manim_code_blocks-1.0.13.dist-info/top_level.txt
manim_code_blocks-1.0.13.dist-info/RECORD
