Metadata-Version: 2.1
Name: manim-code-blocks
Version: 1.0.13
Summary: Animate highlighted blocks of code in Manim
Author: Nicholas Iapalucci
License: MIT License
Project-URL: Homepage, https://github.com/NicholasIapalucci/Manim-Code-Blocks
Classifier: License :: OSI Approved :: MIT License
Classifier: Programming Language :: Python :: 3
Classifier: Operating System :: OS Independent
Requires-Python: >=3.9
License-File: LICENSE
Requires-Dist: tokenize-all
